[
{
    "id": 1,
    "name": "ফুলস্ট্যাক ডেভেলপমেন্ট",
    "thumb": "thumbnail/products/full_stack_development.png",
    "rating": 4.7,
    "start": "2021-05-22",
    "end": "2021-05-25",
    "pill": "gpill",
    "review": "ফুলস্ট্যাক ডেভেলপমেন্ট শেখার একটি অসাধারণ কোর্স।"
  },
    {
    "id": 2,
    "name": "2 ফুলস্ট্যাক ডেভেলপমেন্ট",
    "thumb": "thumbnail/products/full_stack_development.png",
    "rating": 0.00,
    "start": "2021-05-22",
    "end": "2021-05-25",
    "pill": "gpill",
    "review": "ফুলস্ট্যাক ডেভেলপমেন্ট শেখার একটি অসাধারণ কোর্স।"
  }
]
